kornia_moons/__init__.py
kornia_moons/_modidx.py
kornia_moons/_nbdev.py
kornia_moons/feature.py
kornia_moons/line.py
kornia_moons/viz.py
kornia_moons-0.2.9.dist-info/LICENSE
kornia_moons-0.2.9.dist-info/METADATA
kornia_moons-0.2.9.dist-info/WHEEL
kornia_moons-0.2.9.dist-info/entry_points.txt
kornia_moons-0.2.9.dist-info/top_level.txt
kornia_moons-0.2.9.dist-info/RECORD
