Metadata-Version: 2.1
Name: kornia-moons
Version: 0.2.9
Summary: Conversions between kornia and other computer vision libraries formats
Home-page: https://github.com/ducha-aiki/kornia_moons/
Author: Dmytro Mishkin
Author-email: ducha.aiki@gmail.com
License: Apache Software License 2.0
Keywords: kornia,python,pytorch,deep learning,computer vision
Classifier: Development Status :: 3 - Alpha
Classifier: Intended Audience :: Developers
Classifier: Natural Language :: English
Classifier: Programming Language :: Python :: 3.7
Classifier: Programming Language :: Python :: 3.8
Classifier: Programming Language :: Python :: 3.9
Classifier: Programming Language :: Python :: 3.10
Classifier: License :: OSI Approved :: Apache Software License
Requires-Python: >=3.7
License-File: LICENSE
Requires-Dist: kornia
Requires-Dist: torch
Requires-Dist: matplotlib
Requires-Dist: opencv-python
Provides-Extra: dev
